tokenvault/__init__.py
tokenvault/cli.py
tokenvault/config.py
tokenvault-0.1.1.dist-info/licenses/LICENSE
tokenvault-0.1.1.dist-info/METADATA
tokenvault-0.1.1.dist-info/WHEEL
tokenvault-0.1.1.dist-info/entry_points.txt
tokenvault-0.1.1.dist-info/top_level.txt
tokenvault-0.1.1.dist-info/RECORD
