Metadata-Version: 2.4
Name: tokenvault
Version: 0.1.1
Summary: A lightweight package to manage tokens in your application in a single encrypted file and asymmetric token encryption.
License: MIT License
Project-URL: Homepage, https://xethub.com/xdssio/token-vault
Keywords: cryptography,vault,user management,cli,jwt,token,encryption,asymmetric,fastapi
Classifier: License :: OSI Approved :: MIT License
Classifier: Programming Language :: Python
Classifier: Programming Language :: Python :: 3
Requires-Python: >=3.7
License-File: LICENSE
Requires-Dist: pyjwt
Requires-Dist: cryptography
Requires-Dist: typer
Requires-Dist: pyperclip
Provides-Extra: dev
Requires-Dist: pytest; extra == "dev"
Requires-Dist: pytest-cov; extra == "dev"
Requires-Dist: fastapi; extra == "dev"
Requires-Dist: uvicorn; extra == "dev"
Requires-Dist: httpx; extra == "dev"
Dynamic: license-file
